Workbook

Sheet Notes
A1: Source: 'Entreprises et marques utilisant le Nutri-Score en France' (PDF, 38 pages). Title page says Avril 2024; the file name says janvier 2024.
A2: Extraction: table cells read from the PDF's own grid lines, so each row of the PDF = one row here. 1,406 table rows found; 1 is completely blank in the PDF (page 25, between NEWREST FRANCE LE BOURGET and NL International France) and was dropped -> 1,405 companies.
A3: Companies sheet: one row per company, brands exactly as written in the PDF (line wraps removed).
A4: Brands sheet: one row per brand, obtained by splitting the brand cell on commas/semicolons (LIDL: on ' - '). Best-effort: a brand name containing a comma would be split wrongly.
A5: Brand count (Companies!D) is a formula counting that company's rows in Brands.
A6: Review flag: rows where the PDF is ambiguous - several legal entities in one cell, empty/placeholder brand ('aucune', 'No name', 'Marque générique', etc.), partial lists ('25 marques concernées. Par exemple...'), or obviously wrong content (e.g. 'Umsatzsteuer-IdNr.').
A7: Values are kept verbatim (typos, capitalisation, duplicates such as 'Val de Luce' appearing twice are NOT corrected).

Sheet Companies
A1: Company ID | B1: Company | C1: Brands (as listed in PDF) | D1: Brand count (split) | E1: PDF page | F1: Review flag
A2: 1 | B2: 100% Ty'bigoud | C2: 100% Ty'bigoud | D2: =COUNTIF(Brands!$A:$A,A2) -> 1 | E2: 1
A3: 2 | B3: 110 GRAINES | C3: 110 Graines | D3: =COUNTIF(Brands!$A:$A,A3) -> 1 | E3: 1
A4: 3 | B4: 3615 soda | C4: Simple Vice | D4: =COUNTIF(Brands!$A:$A,A4) -> 1 | E4: 1
A5: 4 | B5: 4Retail | C5: Zagazoe | D5: =COUNTIF(Brands!$A:$A,A5) -> 1 | E5: 1
A6: 5 | B6: 4ULTRA | C6: 4ULTRA | D6: =COUNTIF(Brands!$A:$A,A6) -> 1 | E6: 1
A7: 6 | B7: 5M DEVELOPMENT | C7: STARTINE | D7: =COUNTIF(Brands!$A:$A,A7) -> 1 | E7: 1
A8: 7 | B8: 77 FOODS | C8: LA VIE | D8: =COUNTIF(Brands!$A:$A,A8) -> 1 | E8: 1
A9: 8 | B9: A&O L'EPICERIE LOCALE | C9: A&O | D9: =COUNTIF(Brands!$A:$A,A9) -> 1 | E9: 1
A10: 9 | B10: A.C.V. FOOD | C10: Version Crue | D10: =COUNTIF(Brands!$A:$A,A10) -> 1 | E10: 1
A11: 10 | B11: AAPACK UG | C11: Spicywelt | D11: =COUNTIF(Brands!$A:$A,A11) -> 1 | E11: 1
A12: 11 | B12: Aarts Conserven BV | C12: Aarts | D12: =COUNTIF(Brands!$A:$A,A12) -> 1 | E12: 1
A13: 12 | B13: ABCD NUTRITION | C13: Ma boulangerie sans gluten | D13: =COUNTIF(Brands!$A:$A,A13) -> 1 | E13: 1
... A40: 39 | B40: Al Wadi Al Akhdar | C40: Al Wadi Al Akhdar | D40: =COUNTIF(Brands!$A:$A,A40) -> 1 | E40: 2
A41: 40 | B41: Aldi | C41: 25 marques concernées. Par exemple : Les Doris, Drizz, All seasons, Chevrefin, Conquérant, Swing, Golden bridge, Mr frites, Baccara, ADRIEN DELBOS, ALBONA, ARCHIPEL, ARIZONA, ASIA, GREEN, GARDEN, BELLE D'ALSACE, BERGER COMTOIS, BISTRO'VITE, Bon & Vég, BON-RI, BOUCHERIE St Clément, BOURG, BUTTELLA, CASA MORANDO, CHAMPRE, CHANTOISEAU, Château, CLAIRE ET LUCIE, CORRIL, CRACK'HOUR, CROC'MATIN, CROUSTI VOL, CRUST'OCEAN, D'ANTELLI, DELICATO, DELI'SALADES, MyVay, Mama Mancini, Westminster... | D41: =COUNTIF(Brands!$A:$A,A41) -> 40 | E41: 2 | F41: 3 legal entities (ALDI FR/PT/PL) listed in one row; Brand cell is not a real brand name or is a partial list - check; Brand list truncated in PDF ("...")
A42: 41 | B42: Aleksandra Ristic (E-commerce Shop) | C42: Aleksandra Ristic The Bio Foods | D42: =COUNTIF(Brands!$A:$A,A42) -> 1 | E42: 2
A43: 42 | B43: ALGA FOOD | C43: Julienne | D43: =COUNTIF(Brands!$A:$A,A43) -> 1 | E43: 2
A44: 43 | B44: Algorapolis | C44: Algorapolis | D44: =COUNTIF(Brands!$A:$A,A44) -> 1 | E44: 2
A45: 44 | B45: ALGROUPE | C45: ALGOOD | D45: =COUNTIF(Brands!$A:$A,A45) -> 1 | E45: 2
A46: 45 | B46: Alimentation Santé Collectivité | C46: Les Halles Solanid | D46: =COUNTIF(Brands!$A:$A,A46) -> 1 | E46: 2
A47: 46 | B47: ALISA | C47: Graines d'Alisa | D47: =COUNTIF(Brands!$A:$A,A47) -> 1 | E47: 2
A48: 47 | B48: ALL FREEZ NV | C48: All Freez | D48: =COUNTIF(Brands!$A:$A,A48) -> 1 | E48: 2
A49: 48 | B49: All Markets Europe | C49: Vita Coco | D49: =COUNTIF(Brands!$A:$A,A49) -> 1 | E49: 2
A50: 49 | B50: ALLIANCE OCEANE | C50: CORAYA | D50: =COUNTIF(Brands!$A:$A,A50) -> 1 | E50: 2
A51: 50 | B51: Allive Europe UAB | C51: Planet Superfood | D51: =COUNTIF(Brands!$A:$A,A51) -> 1 | E51: 2
A52: 51 | B52: Allmedica Arzneimittel GmbH | C52: Sheko | D52: =COUNTIF(Brands!$A:$A,A52) -> 1 | E52: 2
A53: 52 | B53: Alma & Valor, Lda. | C53: Iswari,Shine | D53: =COUNTIF(Brands!$A:$A,A53) -> 2 | E53: 2
... A81: 80 | B81: Aradi | C81: Aradi un moment de plaisir | D81: =COUNTIF(Brands!$A:$A,A81) -> 1 | E81: 3
A82: 81 | B82: ARC FOOD France | C82: No Name (produit commercialisé sans marque) | D82: =COUNTIF(Brands!$A:$A,A82) -> 1 | E82: 3 | F82: Brand cell is not a real brand name or is a partial list - check
A83: 82 | B83: ARCAL | C83: Prince de Bretagne | D83: =COUNTIF(Brands!$A:$A,A83) -> 1 | E83: 3
A84: 83 | B84: ARCHER Pascal | C84: respect des saveurs | D84: =COUNTIF(Brands!$A:$A,A84) -> 1 | E84: 3
A85: 84 | B85: ARCHIBALD GOURMET | C85: ARCHIBALD GOURMET | D85: =COUNTIF(Brands!$A:$A,A85) -> 1 | E85: 3
A86: 85 | B86: Argenta Schokoladenmanufaktur GmbH | C86: Doucer, GOURMET, Isaura | D86: =COUNTIF(Brands!$A:$A,A86) -> 3 | E86: 3
A87: 86 | B87: ARNAL SAS | C87: GRANVAL, SEBASTIEN DE KERDOUR, D'ARMOR & D'ARGOAT | D87: =COUNTIF(Brands!$A:$A,A87) -> 3 | E87: 3
A88: 87 | B88: ARRIVE S.A.S | C88: MAITRE COQ | D88: =COUNTIF(Brands!$A:$A,A88) -> 1 | E88: 3
A89: 88 | B89: ASSEMAN DEPREZ | C89: VIDELYS | D89: =COUNTIF(Brands!$A:$A,A89) -> 1 | E89: 3
A90: 89 | B90: association des agriculteurs du pays de Lorient | C90: BREIZH POSITIVE | D90: =COUNTIF(Brands!$A:$A,A90) -> 1 | E90: 3
A91: 90 | B91: ATELIER TECHNOLOGIQUE DE L'EPLEFPA DE SAINT-LÔ THERE | C91: LES ENFANTS THERIBLES | D91: =COUNTIF(Brands!$A:$A,A91) -> 1 | E91: 3
A92: 91 | B92: A-TEX | C92: LES DEUX PAGODES | D92: =COUNTIF(Brands!$A:$A,A92) -> 1 | E92: 3
A93: 92 | B93: Atlantique Alimentaire | C93: No name | D93: =COUNTIF(Brands!$A:$A,A93) -> 1 | E93: 3 | F93: Brand cell is not a real brand name or is a partial list - check
A94: 93 | B94: Au blé d'or | C94: Au Blé D'or | D94: =COUNTIF(Brands!$A:$A,A94) -> 1 | E94: 3
A95: 94 | B95: Au pied de mon arbre | C95: Au pied de mon arbre | D95: =COUNTIF(Brands!$A:$A,A95) -> 1 | E95: 3
A96: 95 | B96: AU ROYAUME DES DATTES | C96: Au Royaume Des Dattes | D96: =COUNTIF(Brands!$A:$A,A96) -> 1 | E96: 3
A97: 96 | B97: AUCHAN FRANCE | C97: AUCHAN | D97: =COUNTIF(Brands!$A:$A,A97) -> 1 | E97: 3
A98: 97 | B98: AUGA group, AB | C98: AUGA | D98: =COUNTIF(Brands!$A:$A,A98) -> 1 | E98: 3
A99: 98 | B99: Auprès des laitiers | C99: Auprès des laitiers | D99: =COUNTIF(Brands!$A:$A,A99) -> 1 | E99: 3
A100: 99 | B100: AVBM SAS | C100: Life Loving Foods | D100: =COUNTIF(Brands!$A:$A,A100) -> 1 | E100: 4
A101: 100 | B101: Avêna | C101: Avêna | D101: =COUNTIF(Brands!$A:$A,A101) -> 1 | E101: 4
A102: 101 | B102: AVIFERME | C102: Lustucru ; KOKOT | D102: =COUNTIF(Brands!$A:$A,A102) -> 2 | E102: 4
A103: 102 | B103: AZAIS-POLTIO | C103: LE GOURMAND | D103: =COUNTIF(Brands!$A:$A,A103) -> 1 | E103: 4
A104: 103 | B104: Babetto | C104: Babetto | D104: =COUNTIF(Brands!$A:$A,A104) -> 1 | E104: 4
A105: 104 | B105: Bahier SAS | C105: BAHIER | D105: =COUNTIF(Brands!$A:$A,A105) -> 1 | E105: 4
... A130: 129 | B130: Beyond meat | C130: Beyond Meat EU B.V. | D130: =COUNTIF(Brands!$A:$A,A130) -> 1 | E130: 4
A131: 130 | B131: Bhars Portugal Lda | C131: Recherche, développement, commercialisation d'aliments sains | D131: =COUNTIF(Brands!$A:$A,A131) -> 3 | E131: 4 | F131: Brand cell is not a real brand name or is a partial list - check
A132: 131 | B132: Bio Greenz | C132: Greenz | D132: =COUNTIF(Brands!$A:$A,A132) -> 1 | E132: 4
A133: 132 | B133: Bio Polis | C133: PAIN AU NATUREL | D133: =COUNTIF(Brands!$A:$A,A133) -> 1 | E133: 4
A134: 133 | B134: BIO PRODUCTS FACTORY LIMITED LIABILITY COMPANY (BIO PRODUCTS FACTORY LLC) | C134: TM BØNNER | D134: =COUNTIF(Brands!$A:$A,A134) -> 1 | E134: 4
A135: 134 | B135: BIO TEA FULL H | C135: Bioteafull épicerie | D135: =COUNTIF(Brands!$A:$A,A135) -> 1 | E135: 4
A136: 135 | B136: Bio’goudene pasta | C136: Bio’goudene pasta | D136: =COUNTIF(Brands!$A:$A,A136) -> 1 | E136: 4
A137: 136 | B137: BIOFAIR NUTRITION | C137: BIOFAIR NUTRITION | D137: =COUNTIF(Brands!$A:$A,A137) -> 1 | E137: 5
A138: 137 | B138: BIOFOURNIL | C138: Biofournil, Angélus | D138: =COUNTIF(Brands!$A:$A,A138) -> 2 | E138: 5
A139: 138 | B139: BIOFUTURE | C139: Quintesens | D139: =COUNTIF(Brands!$A:$A,A139) -> 1 | E139: 5
A140: 139 | B140: Bionoor | C140: Bionoor | D140: =COUNTIF(Brands!$A:$A,A140) -> 1 | E140: 5
A141: 140 | B141: BIOOM | C141: BIOOM | D141: =COUNTIF(Brands!$A:$A,A141) -> 1 | E141: 5
A142: 141 | B142: BIOPOP | C142: BIOPOP | D142: =COUNTIF(Brands!$A:$A,A142) -> 1 | E142: 5
A143: 142 | B143: BIORGANE | C143: BIORGANE | D143: =COUNTIF(Brands!$A:$A,A143) -> 1 | E143: 5
... A155: 154 | B155: Blue Skies Holdings Ltd | C155: Blue Skies | D155: =COUNTIF(Brands!$A:$A,A155) -> 1 | E155: 5
A156: 155 | B156: bnjkm | C156: sdfgvhbjnkml | D156: =COUNTIF(Brands!$A:$A,A156) -> 1 | E156: 5 | F156: Brand cell is not a real brand name or is a partial list - check
A157: 156 | B157: BODY IP GmbH | C157: Cereals | D157: =COUNTIF(Brands!$A:$A,A157) -> 1 | E157: 5
A158: 157 | B158: BOEHLI | C158: BOEHLI | D158: =COUNTIF(Brands!$A:$A,A158) -> 1 | E158: 5
A159: 158 | B159: BOFROST*FRANCE | C159: bofrost* | D159: =COUNTIF(Brands!$A:$A,A159) -> 1 | E159: 5
A160: 159 | B160: BONDUELLE Europe Long Life | C160: CASSEGRAIN, VALFRAY | D160: =COUNTIF(Brands!$A:$A,A160) -> 2 | E160: 5
A161: 160 | B161: BONDUELLE SA | C161: Bonduelle, BONDUELLE FOOD SERVICE, T'es trop fresh | D161: =COUNTIF(Brands!$A:$A,A161) -> 3 | E161: 5
A162: 161 | B162: BONTOUT SA | C162: BONTOUT | D162: =COUNTIF(Brands!$A:$A,A162) -> 1 | E162: 5
A163: 162 | B163: BORDE | C163: BORDE, Les Montagnards | D163: =COUNTIF(Brands!$A:$A,A163) -> 2 | E163: 5
A164: 163 | B164: Boucherie Charcuterie Balkanique | C164: La Bouletterie | D164: =COUNTIF(Brands!$A:$A,A164) -> 1 | E164: 5
A165: 164 | B165: BOULANGERIE LE ROUX | C165: AVELLANN | D165: =COUNTIF(Brands!$A:$A,A165) -> 1 | E165: 5
A166: 165 | B166: Boulangerie Neuhauser SA | C166: LE PETIT FRANCAIS / DOLCE DE NATA | D166: =COUNTIF(Brands!$A:$A,A166) -> 1 | E166: 5
A167: 166 | B167: Boulogne Seafood | C167: BOULOGNE SEAFOOD | D167: =COUNTIF(Brands!$A:$A,A167) -> 1 | E167: 5
A168: 167 | B168: BP TRACE | C168: B4FOOD | D168: =COUNTIF(Brands!$A:$A,A168) -> 1 | E168: 5
... A297: 296 | B297: Crous de Lyon | C297: Crous de Lyon | D297: =COUNTIF(Brands!$A:$A,A297) -> 1 | E297: 9
A298: 297 | B298: CROUS DE STRASBOURG | C298: aucune | D298: =COUNTIF(Brands!$A:$A,A298) -> 1 | E298: 9 | F298: Brand cell is not a real brand name or is a partial list - check
A299: 298 | B299: Crous de Toulouse-Occitanie | C299: Crous de Toulouse-Occitanie | D299: =COUNTIF(Brands!$A:$A,A299) -> 1 | E299: 9
A300: 299 | B300: Crous Montpellier Occitanie | C300: Crous Resto | D300: =COUNTIF(Brands!$A:$A,A300) -> 1 | E300: 9
A301: 300 | B301: CRUSTA C | C301: CRUSTA C | D301: =COUNTIF(Brands!$A:$A,A301) -> 1 | E301: 9
A302: 301 | B302: CUI ZSQ FOOD, S.L. | C302: KANGLE , SHUANGHE , PASTAS IBERIA | D302: =COUNTIF(Brands!$A:$A,A302) -> 3 | E302: 9
A303: 302 | B303: CUISINE & RECEPTION SARL | C303: Perret Cuisine et Convivialité | D303: =COUNTIF(Brands!$A:$A,A303) -> 1 | E303: 9
A304: 303 | B304: cultimer | C304: aucune | D304: =COUNTIF(Brands!$A:$A,A304) -> 1 | E304: 9 | F304: Brand cell is not a real brand name or is a partial list - check
A305: 304 | B305: Cupana | C305: Cupana | D305: =COUNTIF(Brands!$A:$A,A305) -> 1 | E305: 9
A306: 305 | B306: Curtice Brothers | C306: Curtice Brothers | D306: =COUNTIF(Brands!$A:$A,A306) -> 1 | E306: 9
A307: 306 | B307: Cutie Pie | C307: Kit and Cook | D307: =COUNTIF(Brands!$A:$A,A307) -> 1 | E307: 9
A308: 307 | B308: DACO FRANCE | C308: Daco Bello | D308: =COUNTIF(Brands!$A:$A,A308) -> 1 | E308: 9
A309: 308 | B309: Daesang Europe BV | C309: O Food, Jongga | D309: =COUNTIF(Brands!$A:$A,A309) -> 2 | E309: 9
A310: 309 | B310: DAILY PIC HOLIDING | C310: DAILY PIC | D310: =COUNTIF(Brands!$A:$A,A310) -> 1 | E310: 9
A311: 310 | B311: Dailycieux | C311: Dailycieux | D311: =COUNTIF(Brands!$A:$A,A311) -> 1 | E311: 9
A312: 311 | B312: DamaBeautanica | C312: Vitashoot | D312: =COUNTIF(Brands!$A:$A,A312) -> 1 | E312: 9
A313: 312 | B313: DAMIEN DE JONG | C313: DAM, Ô goût du terroir | D313: =COUNTIF(Brands!$A:$A,A313) -> 2 | E313: 9
A314: 313 | B314: D'ANGELO PASTA | C314: D'ANGELO PASTA | D314: =COUNTIF(Brands!$A:$A,A314) -> 1 | E314: 9
A315: 314 | B315: Daniel Allaire SAS | C315: Maison Allaire | D315: =COUNTIF(Brands!$A:$A,A315) -> 1 | E315: 9
A316: 315 | B316: DANIVAL | C316: La néopopote | D316: =COUNTIF(Brands!$A:$A,A316) -> 1 | E316: 9
...

Sheet Brands
A1: Company ID | B1: Company | C1: Brand
A2: 1 | B2: 100% Ty'bigoud | C2: 100% Ty'bigoud
A3: 2 | B3: 110 GRAINES | C3: 110 Graines
A4: 3 | B4: 3615 soda | C4: Simple Vice
A5: 4 | B5: 4Retail | C5: Zagazoe
A6: 5 | B6: 4ULTRA | C6: 4ULTRA
A7: 6 | B7: 5M DEVELOPMENT | C7: STARTINE
A8: 7 | B8: 77 FOODS | C8: LA VIE
A9: 8 | B9: A&O L'EPICERIE LOCALE | C9: A&O
A10: 9 | B10: A.C.V. FOOD | C10: Version Crue
A11: 10 | B11: AAPACK UG | C11: Spicywelt
A12: 11 | B12: Aarts Conserven BV | C12: Aarts
A13: 12 | B13: ABCD NUTRITION | C13: Ma boulangerie sans gluten
... A1795: 1405 | B1795: ТОВ "ОРЕКС ДІСТРІБЬЮШЕН" | C1795: HLIBO
